{
    "key": "group_omb_case_study_settings",
    "title": "OMB Case Study",
    "fields": [
        {
            "key": "field_omb_case_study_project_label",
            "label": "Project label",
            "name": "case_study_project_label",
            "aria-label": "",
            "type": "text",
            "instructions": "Shown above the title on overview cards and on the single template (e.g. “Project: Voetzorg Roermond”).",
            "required": 0,
            "conditional_logic": 0,
            "wrapper": {
                "width": "",
                "class": "",
                "id": ""
            },
            "default_value": "",
            "maxlength": "",
            "allow_in_bindings": 0,
            "placeholder": "",
            "prepend": "",
            "append": ""
        },
        {
            "key": "field_omb_case_study_outcome_metrics",
            "label": "Outcome metrics",
            "name": "case_study_outcome_metrics",
            "aria-label": "",
            "type": "repeater",
            "instructions": "Metrics for the overview featured block (first three used there) and for the **single case study** metrics bar (all rows, typically four).",
            "required": 0,
            "conditional_logic": 0,
            "wrapper": {
                "width": "",
                "class": "",
                "id": ""
            },
            "layout": "row",
            "pagination": 0,
            "min": 0,
            "max": 8,
            "collapsed": "",
            "button_label": "Add metric",
            "rows_per_page": 20,
            "sub_fields": [
                {
                    "key": "field_omb_case_study_metric_label",
                    "label": "Label",
                    "name": "metric_label",
                    "aria-label": "",
                    "type": "text",
                    "instructions": "",
                    "required": 0,
                    "conditional_logic": 0,
                    "wrapper": {
                        "width": "",
                        "class": "",
                        "id": ""
                    },
                    "default_value": "",
                    "maxlength": "",
                    "allow_in_bindings": 0,
                    "placeholder": "",
                    "prepend": "",
                    "append": "",
                    "parent_repeater": "field_omb_case_study_outcome_metrics"
                },
                {
                    "key": "field_omb_case_study_metric_value",
                    "label": "Value",
                    "name": "metric_value",
                    "aria-label": "",
                    "type": "text",
                    "instructions": "",
                    "required": 0,
                    "conditional_logic": 0,
                    "wrapper": {
                        "width": "",
                        "class": "",
                        "id": ""
                    },
                    "default_value": "",
                    "maxlength": "",
                    "allow_in_bindings": 0,
                    "placeholder": "",
                    "prepend": "",
                    "append": "",
                    "parent_repeater": "field_omb_case_study_outcome_metrics"
                }
            ]
        },
        {
            "key": "field_omb_case_study_lead",
            "label": "Case study lead (on-page intro)",
            "name": "case_study_lead",
            "aria-label": "",
            "type": "wysiwyg",
            "instructions": "Optional intro under the title. When empty, the WordPress excerpt is shown as plain text (same idea as blog **Post lead**).",
            "required": 0,
            "conditional_logic": 0,
            "wrapper": {
                "width": "",
                "class": "",
                "id": ""
            },
            "default_value": "",
            "allow_in_bindings": 1,
            "tabs": "visual",
            "toolbar": "basic",
            "media_upload": 0,
            "delay": 0
        },
        {
            "key": "field_omb_case_study_show_toc",
            "label": "Show table of contents",
            "name": "show_toc",
            "aria-label": "",
            "type": "true_false",
            "instructions": "When off, the Inhoudsopgave block is hidden (author card still shows).",
            "required": 0,
            "conditional_logic": 0,
            "wrapper": {
                "width": "",
                "class": "",
                "id": ""
            },
            "message": "",
            "default_value": 1,
            "ui": 1,
            "ui_on_text": "Yes",
            "ui_off_text": "No"
        },
        {
            "key": "field_omb_case_study_breadcrumb_parent",
            "label": "Breadcrumb parent (before case studies)",
            "name": "breadcrumb_parent",
            "aria-label": "",
            "type": "link",
            "instructions": "Optional first breadcrumb segment before the case studies archive link.",
            "required": 0,
            "conditional_logic": 0,
            "wrapper": {
                "width": "",
                "class": "",
                "id": ""
            },
            "return_format": "array",
            "allow_in_bindings": 1
        },
        {
            "key": "field_omb_case_study_show_related",
            "label": "Show related case studies",
            "name": "show_related_case_studies",
            "aria-label": "",
            "type": "true_false",
            "instructions": "When on, three other case studies load at the bottom of the single template.",
            "required": 0,
            "conditional_logic": 0,
            "wrapper": {
                "width": "",
                "class": "",
                "id": ""
            },
            "message": "",
            "default_value": 1,
            "ui": 1,
            "ui_on_text": "Yes",
            "ui_off_text": "No"
        },
        {
            "key": "field_omb_case_study_featured_form",
            "label": "Featured form",
            "name": "featured_form",
            "aria-label": "",
            "type": "post_object",
            "instructions": "Optional Contact Form 7 form embedded after the article body (same pattern as blog posts).",
            "required": 0,
            "conditional_logic": 0,
            "wrapper": {
                "width": "",
                "class": "",
                "id": ""
            },
            "post_type": [
                "wpcf7_contact_form"
            ],
            "post_status": [
                "publish"
            ],
            "taxonomy": "",
            "return_format": "object",
            "multiple": 0,
            "allow_null": 1,
            "allow_in_bindings": 0,
            "bidirectional": 0,
            "ui": 1,
            "bidirectional_target": []
        }
    ],
    "location": [
        [
            {
                "param": "post_type",
                "operator": "==",
                "value": "case_study"
            }
        ]
    ],
    "menu_order": 0,
    "position": "normal",
    "style": "default",
    "label_placement": "top",
    "instruction_placement": "label",
    "hide_on_screen": "",
    "active": true,
    "description": "",
    "show_in_rest": 1,
    "display_title": "",
    "allow_ai_access": false,
    "ai_description": "",
    "modified": 1779500000
}
